opensemantic/base/__init__.py
opensemantic/base/_model.py
opensemantic_base-0.30.0.dev1.dist-info/licenses/LICENSE.txt
opensemantic_base-0.30.0.dev1.dist-info/METADATA
opensemantic_base-0.30.0.dev1.dist-info/WHEEL
opensemantic_base-0.30.0.dev1.dist-info/top_level.txt
opensemantic_base-0.30.0.dev1.dist-info/RECORD
