Metadata-Version: 2.4
Name: opensemantic.base
Version: 0.30.0.dev1
Summary: Library with Python models derived from the page package world.opensemantic.base
Home-page: https://github.com/OpenSemanticWorld-Packages/opensemantic.base-python
Author: OpenSemanticWorld
Author-email: team@opensemantic.world
License: Apache 2.0
Project-URL: Documentation, https://github.com/OpenSemanticWorld-Packages/opensemantic.base-python
Project-URL: Source, https://github.com/OpenSemanticWorld-Packages/opensemantic.base-python
Project-URL: Tracker, https://github.com/OpenSemanticWorld-Packages/opensemantic.base-python/issues
Platform: any
Classifier: Development Status :: 4 - Beta
Classifier: Programming Language :: Python
Requires-Python: >=3.9
License-File: LICENSE.txt
Requires-Dist: opensemantic.core
Requires-Dist: pydantic[email]
Provides-Extra: testing
Requires-Dist: setuptools; extra == "testing"
Requires-Dist: pytest; extra == "testing"
Requires-Dist: pytest-cov; extra == "testing"
Dynamic: license-file
